nav_sim_modules/__init__.py
nav_sim_modules/actioner/__init__.py
nav_sim_modules/actioner/actioner.py
nav_sim_modules/actioner/hueristic_autonomous_actioner/__init__.py
nav_sim_modules/actioner/hueristic_autonomous_actioner/actioner.py
nav_sim_modules/actioner/hueristic_autonomous_actioner/autonomous.py
nav_sim_modules/nav_components/__init__.py
nav_sim_modules/nav_components/__init__.pyx
nav_sim_modules/nav_components/mapping.pyx
nav_sim_modules/nav_components/planning.pyx
nav_sim_modules/scener/__init__.py
nav_sim_modules/scener/chest_search_room/__init__.py
nav_sim_modules/scener/chest_search_room/scener.py
nav_sim_modules/scener/scener.py
nav_sim_modules/utils.py
nav_sim_modules/nav_components/mapping.cpython-38-x86_64-linux-gnu.so
nav_sim_modules/nav_components/mapping.cpp
nav_sim_modules/nav_components/planning.cpython-38-x86_64-linux-gnu.so
nav_sim_modules/nav_components/planning.cpp
nav_sim_modules-0.3.9.dist-info/WHEEL
nav_sim_modules-0.3.9.dist-info/METADATA
nav_sim_modules-0.3.9.dist-info/RECORD
