Metadata-Version: 2.1
Name: nav-sim-modules
Version: 0.3.9
Summary: Components for software to simulate the environment of robot that use autonomous movement system such as ROS Navigation Stack.
Home-page: https://github.com/wwwshwww/nav-sim-modules
Author: Reona Sato
Author-email: www.shinderu.www@gmail.com
Requires-Python: >=3.7,<3.10
Classifier: Programming Language :: Python :: 3
Classifier: Programming Language :: Python :: 3.7
Classifier: Programming Language :: Python :: 3.8
Classifier: Programming Language :: Python :: 3.9
Requires-Dist: Pillow (>=8.4.0,<9.0.0)
Requires-Dist: cython (>=0.29.24,<0.30.0)
Requires-Dist: numba (>=0.54.1,<0.55.0)
Requires-Dist: numpy (>=1.20,<2.0)
Requires-Dist: randoor (>=0.1.4.6,<0.2.0.0)
